<root annotationID="0" passageID="545_0">
  <attributes />
  <extra format="ucca" />
  <layer layerID="0">
    <attributes />
    <extra doc="[[[14143520107006108953, 14143520107006108953, 4969857429396651903, 96, 0, 2, 442, 2, 14143520107006108953, 11221368173670222813, 14143520107006108953], [16331095434822636218, 16331095434822636218, 17524233984504158541, 85, 0, 2, 397, 1, 4088098365541558500, 15817570140490810055, 16331095434822636218], [530855179026533974, 530855179026533974, 10554686591937588953, 83, 0, 2, 8206900633647566924, 0, 13110060611322374290, 15598372446745583797, 6901033109670990563], [17494803046312582752, 17494803046312582752, 12646065887601541794, 96, 0, 2, 442, -1, 17494803046312582752, 17494803046312582752, 17494803046312582752], [16331095434822636218, 16331095434822636218, 17524233984504158541, 85, 0, 2, 397, 1, 4088098365541558500, 15817570140490810055, 16331095434822636218], [530855179026533974, 530855179026533974, 10554686591937588953, 83, 0, 2, 8206900633647566924, 0, 13110060611322374290, 15598372446745583797, 6901033109670990563], [17494803046312582752, 17494803046312582752, 12646065887601541794, 96, 0, 2, 442, -1, 17494803046312582752, 17494803046312582752, 17494803046312582752], [14143520107006108953, 14143520107006108953, 14143520107006108953, 96, 0, 2, 442, -2, 14143520107006108953, 11221368173670222813, 14143520107006108953], [18384085136260030139, 5286809987425472328, 17109001835818727656, 99, 0, 2, 8206900633647566924, 0, 13110060611322374290, 16900879642891266615, 16602120460534419010], [10265832328710632600, 11442637635535914345, 15794550382381185553, 95, 378, 3, 413, -1, 16072095006890171862, 149303876845869574, 9113047341877232477], [null, null, 12646065887601541794, 96, 0, 2, 442, -2, 7673861486741121899, 12646065887601541794, 7673861486741121899]]]" />
    <node ID="0.1" type="Punctuation">
      <attributes paragraph="1" paragraph_position="1" text="''" />
    </node>
    <node ID="0.2" type="Word">
      <attributes paragraph="1" paragraph_position="2" text="how" />
    </node>
    <node ID="0.3" type="Word">
      <attributes paragraph="1" paragraph_position="3" text="beautiful" />
    </node>
    <node ID="0.4" type="Punctuation">
      <attributes paragraph="1" paragraph_position="4" text="!" />
    </node>
    <node ID="0.5" type="Word">
      <attributes paragraph="1" paragraph_position="5" text="how" />
    </node>
    <node ID="0.6" type="Word">
      <attributes paragraph="1" paragraph_position="6" text="beautiful" />
    </node>
    <node ID="0.7" type="Punctuation">
      <attributes paragraph="1" paragraph_position="7" text="!" />
    </node>
    <node ID="0.8" type="Punctuation">
      <attributes paragraph="1" paragraph_position="8" text="''" />
    </node>
    <node ID="0.9" type="Word">
      <attributes paragraph="1" paragraph_position="9" text="cried" />
    </node>
    <node ID="0.10" type="Word">
      <attributes paragraph="1" paragraph_position="10" text="Conseil" />
    </node>
    <node ID="0.11" type="Word">
      <attributes paragraph="1" paragraph_position="11" text=".&#10;" />
    </node>
  </layer>
  <layer layerID="1">
    <attributes />
    <node ID="1.1" type="FN">
      <attributes />
      <edge toID="1.2" type="U">
        <attributes />
      </edge>
      <edge toID="1.3" type="H">
        <attributes />
      </edge>
    </node>
    <node ID="1.2" type="PNCT">
      <attributes />
      <edge toID="0.1" type="Terminal">
        <attributes />
      </edge>
    </node>
    <node ID="1.3" type="FN">
      <attributes />
      <edge toID="1.4" type="D">
        <attributes />
      </edge>
      <edge toID="1.5" type="S">
        <attributes />
      </edge>
      <edge toID="1.6" type="U">
        <attributes />
      </edge>
      <edge toID="1.7" type="A">
        <attributes />
      </edge>
    </node>
    <node ID="1.4" type="FN">
      <attributes />
      <edge toID="0.2" type="Terminal">
        <attributes />
      </edge>
    </node>
    <node ID="1.5" type="FN">
      <attributes />
      <edge toID="0.3" type="Terminal">
        <attributes />
      </edge>
    </node>
    <node ID="1.6" type="PNCT">
      <attributes />
      <edge toID="0.4" type="Terminal">
        <attributes />
      </edge>
    </node>
    <node ID="1.7" type="FN">
      <attributes />
      <edge toID="1.8" type="D">
        <attributes />
      </edge>
      <edge toID="1.9" type="P">
        <attributes />
      </edge>
      <edge toID="1.10" type="U">
        <attributes />
      </edge>
      <edge toID="1.11" type="A">
        <attributes />
      </edge>
    </node>
    <node ID="1.8" type="FN">
      <attributes />
      <edge toID="0.5" type="Terminal">
        <attributes />
      </edge>
    </node>
    <node ID="1.9" type="FN">
      <attributes />
      <edge toID="0.6" type="Terminal">
        <attributes />
      </edge>
    </node>
    <node ID="1.10" type="PNCT">
      <attributes />
      <edge toID="0.7" type="Terminal">
        <attributes />
      </edge>
    </node>
    <node ID="1.11" type="FN">
      <attributes />
      <edge toID="1.12" type="U">
        <attributes />
      </edge>
      <edge toID="1.13" type="P">
        <attributes />
      </edge>
      <edge toID="1.14" type="A">
        <attributes />
      </edge>
    </node>
    <node ID="1.12" type="PNCT">
      <attributes />
      <edge toID="0.8" type="Terminal">
        <attributes />
      </edge>
    </node>
    <node ID="1.13" type="FN">
      <attributes />
      <edge toID="0.9" type="Terminal">
        <attributes />
      </edge>
    </node>
    <node ID="1.14" type="FN">
      <attributes />
      <edge toID="0.10" type="Terminal">
        <attributes />
      </edge>
      <edge toID="0.11" type="Terminal">
        <attributes />
      </edge>
    </node>
  </layer>
</root>
